napplib/__init__.py
napplib/azure/__init__.py
napplib/azure/azure_queue.py
napplib/azure/blob_storage.py
napplib/b2w/__init__.py
napplib/b2w/controller.py
napplib/b2w/utils.py
napplib/b2w/models/__init__.py
napplib/b2w/models/order.py
napplib/b2w/models/product.py
napplib/bling/__init__.py
napplib/bling/controller.py
napplib/bling/utils.py
napplib/business_shop/__init__.py
napplib/business_shop/controller.py
napplib/cigam/__init__.py
napplib/cigam/gestor/__init__.py
napplib/cigam/gestor/controller.py
napplib/commerce_plus/__init__.py
napplib/commerce_plus/controller.py
napplib/delivery_center/__init__.py
napplib/delivery_center/controller.py
napplib/delivery_center/models/__init__.py
napplib/delivery_center/models/inventory.py
napplib/delivery_center/models/product.py
napplib/facebook/__init__.py
napplib/facebook/controller.py
napplib/facebook/models/__init__.py
napplib/facebook/models/products.py
napplib/farmacias_app/__init__.py
napplib/farmacias_app/controller.py
napplib/farmacias_app/models/__init__.py
napplib/farmacias_app/models/authorization.py
napplib/farmacias_app/models/product.py
napplib/ftp/__init__.py
napplib/ftp/controller.py
napplib/google/GetAttachments.py
napplib/google/GoogleDrive.py
napplib/google/__init__.py
napplib/google/errors.py
napplib/google/google_api.py
napplib/hiper_ecommerce/__init__.py
napplib/hiper_ecommerce/controller.py
napplib/hiper_ecommerce/models/__init__.py
napplib/hub/__init__.py
napplib/hub/controller.py
napplib/hub/utils.py
napplib/hub/models/__init__.py
napplib/hub/models/order.py
napplib/hub/models/product.py
napplib/hub/v1_1/__init__.py
napplib/hub/v1_1/controller.py
napplib/hub/v1_1/utils.py
napplib/hub/v1_1/models/__init__.py
napplib/hub/v1_1/models/product.py
napplib/hub/v2/__init__.py
napplib/hub/v2/controller.py
napplib/hub/v2/utils.py
napplib/hub/v2/models/__init__.py
napplib/hub/v2/models/catalog.py
napplib/hub/v2/models/channel.py
napplib/hub/v2/models/message.py
napplib/hub/v2/models/order.py
napplib-0.8.30.4.dist-info/LICENSE
napplib-0.8.30.4.dist-info/METADATA
napplib-0.8.30.4.dist-info/WHEEL
napplib-0.8.30.4.dist-info/top_level.txt
napplib-0.8.30.4.dist-info/RECORD
